{
  "users": [
    {
      "id": 1,
      "name": "adalberto",
      "age": 17,
      "job": "estagiario"
    },
    {
      "id": 2,
      "name": "Jurandir",
      "age": 27,
      "job": "Uber"
    },
    {
      "id": 3,
      "name": "Ermelindo",
      "age": 37,
      "job": "programador"
    },
    {
      "id": 4,
      "name": "josivaldo",
      "age": 47,
      "job": "programador senior"
    },
    {
      "name": "batman",
      "job": "hero",
      "age": "40",
      "id": 6
    }
  ]
}